groq_qa_generator/__init__.py
groq_qa_generator/cli.py
groq_qa_generator/config.json
groq_qa_generator/config.py
groq_qa_generator/data/alices_adventures_in_wonderland.txt
groq_qa_generator/data/prompts/sample_question.txt
groq_qa_generator/data/prompts/system_prompt.txt
groq_qa_generator/data/sample_input_data.txt
groq_qa_generator/dataset_processor.py
groq_qa_generator/groq_api.py
groq_qa_generator/groq_qa.py
groq_qa_generator/huggingface_api.py
groq_qa_generator/logging_setup.py
groq_qa_generator/qa_generation.py
groq_qa_generator/tokenizer.py
groq_qa_generator-1.2.1.dist-info/LICENSE
groq_qa_generator-1.2.1.dist-info/METADATA
groq_qa_generator-1.2.1.dist-info/WHEEL
groq_qa_generator-1.2.1.dist-info/entry_points.txt
groq_qa_generator-1.2.1.dist-info/RECORD
