Metadata-Version: 2.1
Name: groq-qa-generator
Version: 1.2.1
Summary: Groq QA automates question-answer generation from text with LLaMA 3 and Hugging Face to fine-tune large language models (LLMs).
License: MIT
Author: Jordan Cassady
Author-email: jordan.cassady@gmail.com
Requires-Python: >=3.10,<4.0
Classifier: License :: OSI Approved :: MIT License
Classifier: Programming Language :: Python :: 3
Classifier: Programming Language :: Python :: 3.10
Classifier: Programming Language :: Python :: 3.11
Classifier: Programming Language :: Python :: 3.12
Requires-Dist: datasets (>=3.0.1,<4.0.0)
Requires-Dist: groq (>=0.11.0,<0.12.0)
Requires-Dist: huggingface-hub (>=0.25.2,<0.26.0)
Requires-Dist: python-dotenv (>=1.0.1,<2.0.0)
Requires-Dist: tiktoken (>=0.7.0,<0.8.0)
